aliste/__init__.py
aliste/broker.py
aliste/constants.py
aliste/device.py
aliste/enums.py
aliste/home.py
aliste/hub.py
aliste/user.py
aliste/utils.py
aliste-1.0.2.dist-info/LICENSE
aliste-1.0.2.dist-info/METADATA
aliste-1.0.2.dist-info/WHEEL
aliste-1.0.2.dist-info/RECORD
